.gitignore
LICENSE
MANIFEST.in
README.md
setup.py
enhance_djpro_tpl/__init__.py
enhance_djpro_tpl.egg-info/PKG-INFO
enhance_djpro_tpl.egg-info/SOURCES.txt
enhance_djpro_tpl.egg-info/dependency_links.txt
enhance_djpro_tpl.egg-info/top_level.txt
enhance_djpro_tpl/app_template/__init__.py
enhance_djpro_tpl/app_template/admin.py
enhance_djpro_tpl/app_template/models.py
enhance_djpro_tpl/app_template/tests.py
enhance_djpro_tpl/app_template/urls.py
enhance_djpro_tpl/app_template/views.py
enhance_djpro_tpl/project_template/__init__.py
enhance_djpro_tpl/project_template/manage.py
enhance_djpro_tpl/project_template/libs/__init__.py
enhance_djpro_tpl/project_template/libs/oauth2app/__init__.py
enhance_djpro_tpl/project_template/libs/oauth2app/admin.py
enhance_djpro_tpl/project_template/libs/oauth2app/authenticate.py
enhance_djpro_tpl/project_template/libs/oauth2app/authorize.py
enhance_djpro_tpl/project_template/libs/oauth2app/consts.py
enhance_djpro_tpl/project_template/libs/oauth2app/decorators.py
enhance_djpro_tpl/project_template/libs/oauth2app/exceptions.py
enhance_djpro_tpl/project_template/libs/oauth2app/models.py
enhance_djpro_tpl/project_template/libs/oauth2app/token.py
enhance_djpro_tpl/project_template/libs/oauth2app/lib/__init__.py
enhance_djpro_tpl/project_template/libs/oauth2app/lib/uri.py
enhance_djpro_tpl/project_template/libs/oauth2app/lib/url_normalize.py
enhance_djpro_tpl/project_template/libs/tastypie/__init__.py
enhance_djpro_tpl/project_template/libs/tastypie/admin.py
enhance_djpro_tpl/project_template/libs/tastypie/api.py
enhance_djpro_tpl/project_template/libs/tastypie/authentication.py
enhance_djpro_tpl/project_template/libs/tastypie/authorization.py
enhance_djpro_tpl/project_template/libs/tastypie/bundle.py
enhance_djpro_tpl/project_template/libs/tastypie/cache.py
enhance_djpro_tpl/project_template/libs/tastypie/compat.py
enhance_djpro_tpl/project_template/libs/tastypie/constants.py
enhance_djpro_tpl/project_template/libs/tastypie/exceptions.py
enhance_djpro_tpl/project_template/libs/tastypie/fields.py
enhance_djpro_tpl/project_template/libs/tastypie/http.py
