Metadata-Version: 1.0
Name: enhance-djpro-tpl
Version: 0.0.12
Summary: An enhance django project template.
Home-page: UNKNOWN
Author: Maple.Liu
Author-email: fjliufeng@163.com
License: GNU LESSER GENERAL PUBLIC LICENSE
Keywords: enhance,project,template,app,django
Platform: any
